exasol/harlequin/__init__.py
exasol/harlequin/_adapter.py
exasol/harlequin/_catalog.py
exasol/harlequin/_completions.py
exasol/harlequin/_options.py
exasol/harlequin/version.py
harlequin_exasol-0.2.0.dist-info/LICENSE
harlequin_exasol-0.2.0.dist-info/METADATA
harlequin_exasol-0.2.0.dist-info/WHEEL
harlequin_exasol-0.2.0.dist-info/entry_points.txt
harlequin_exasol-0.2.0.dist-info/RECORD
