Metadata-Version: 2.1
Name: harlequin-exasol
Version: 0.2.0
Summary: Harelequin adapter for Exasol
Home-page: https://github.com/nicoretti/harlequin-exasol
License: MIT
Keywords: exasol,harlequin
Author: Nicola Coretti
Author-email: nicola.coretti@exasol.com
Requires-Python: >=3.9,<4.0
Classifier: License :: OSI Approved :: MIT License
Classifier: Programming Language :: Python :: 3
Classifier: Programming Language :: Python :: 3.9
Classifier: Programming Language :: Python :: 3.10
Classifier: Programming Language :: Python :: 3.11
Requires-Dist: harlequin (>=1.22.1,<2.0.0)
Requires-Dist: pyexasol (>=0.26.0)
Project-URL: Repository, https://github.com/nicoretti/harlequin-exasol
